<?xml version="1.0"?>
<?iotk version="1.2.0"?>
<?iotk file_version="1.0"?>
<?iotk binary="F"?>
<?iotk qe_syntax="F"?>
<Root>
  <EQUATIONS_OF_STATE>
    <EQUATION_TYPE type="character" size="1" len="15">
Birch 1st order
    </EQUATION_TYPE>
    <CHI_SQUARE type="real" size="1">
 7.344789202842871E-011
    </CHI_SQUARE>
  </EQUATIONS_OF_STATE>
  <EQUATIONS_PARAMETERS>
    <EQUILIBRIUM_VOLUME_AU_A type="real" size="2" columns="2">
 2.547237209566192E+002  3.774616060011410E+001
    </EQUILIBRIUM_VOLUME_AU_A>
    <BULK_MODULUS_KBAR type="real" size="1">
 7.256091327334474E+001
    </BULK_MODULUS_KBAR>
    <DERIVATIVE_BULK_MODULUS type="real" size="1">
 3.790500184167223E+000
    </DERIVATIVE_BULK_MODULUS>
    <SECOND_DERIVATIVE_BULK_MODULUS type="real" size="1">
 0.000000000000000E+000
    </SECOND_DERIVATIVE_BULK_MODULUS>
    <MINIMUM_ENERGY_RY type="real" size="1">
-9.510608518509122E+001
    </MINIMUM_ENERGY_RY>
    <CELL_FACTOR type="real" size="1">
 2.500000000000000E-001
    </CELL_FACTOR>
    <CELL_PARAMETER_AU_A type="real" size="2" columns="2">
 1.006259037326827E+001  5.324893484910710E+000
    </CELL_PARAMETER_AU_A>
  </EQUATIONS_PARAMETERS>
  <FIT_CHECK>
    <NUMBER_OF_DATA type="integer" size="1">
        13
    </NUMBER_OF_DATA>
    <VOL_ENE_EFIT_DELTA_P_GIBBS type="real" size="78" columns="6">
 1.481820736055420E+002 -9.508055380940785E+001 -9.508055795750236E+001  4.148094518541257E-006  1.088054925919820E+002 -9.497095170484715E+001 
 1.618036562500000E+002 -9.508910446139978E+001 -9.508909662628362E+001 -7.835116164756073E-006  7.737100282708290E+001 -9.500400261885147E+001 
 1.744744861711648E+002 -9.509480034676398E+001 -9.509479696254419E+001 -3.384219780855346E-006  5.603320059754348E+001 -9.502834196470495E+001 
 1.828581752500000E+002 -9.509766347312205E+001 -9.509766468979441E+001  1.216672359305448E-006  4.494969102704947E+001 -9.504178899257417E+001 
 2.004522399750655E+002 -9.510191368765932E+001 -9.510192181757090E+001  8.129911577725579E-006  2.733957224651561E+001 -9.506465950537894E+001 
 2.143437500000000E+002 -9.510400250581387E+001 -9.510401000132488E+001  7.495511013644318E-006  1.735777883637283E+001 -9.507871084311553E+001 
 2.211840000000000E+002 -9.510471114930141E+001 -9.510472256891117E+001  1.141960976269729E-005  1.338117047112949E+001 -9.508459150875451E+001 
 2.281682499999999E+002 -9.510526134503232E+001 -9.510527188299238E+001  1.053796006544871E-005  9.839492620996468E+000 -9.508999973606042E+001 
 2.412875230954168E+002 -9.510588999966153E+001 -9.510589463158905E+001  4.631927524201274E-006  4.357114150923595E+000 -9.509874328884092E+001 
 2.477457206488650E+002 -9.510603719324972E+001 -9.510603590443284E+001 -1.288816875444354E-006  2.124405312477901E+000 -9.510245939418223E+001 
 2.515030020000000E+002 -9.510608035049088E+001 -9.510607493563565E+001 -5.414855237972915E-006  9.458415139128546E-001 -9.510446326138575E+001 
 2.715934879999999E+002 -9.510584944125166E+001 -9.510583653171753E+001 -1.290953413501938E-005 -4.120241226791230E+000 -9.511345645852005E+001 
 2.812160000000001E+002 -9.510552211095987E+001 -9.510550536381503E+001 -1.674714484067863E-005 -5.950615660039141E+000 -9.511689771151022E+001
    </VOL_ENE_EFIT_DELTA_P_GIBBS>
  </FIT_CHECK>
</Root>

