<?xml version="1.0"?>
<?iotk version="1.2.0"?>
<?iotk file_version="1.0"?>
<?iotk binary="F"?>
<?iotk qe_syntax="F"?>
<Root>
  <EQUATIONS_OF_STATE>
    <EQUATION_TYPE type="character" size="1" len="15">
Birch 1st order
    </EQUATION_TYPE>
    <CHI_SQUARE type="real" size="1">
 1.300097728067806E-011
    </CHI_SQUARE>
  </EQUATIONS_OF_STATE>
  <EQUATIONS_PARAMETERS>
    <EQUILIBRIUM_VOLUME_AU_A type="real" size="2" columns="2">
 2.539185731809808E+002  3.762685001085317E+001
    </EQUILIBRIUM_VOLUME_AU_A>
    <BULK_MODULUS_KBAR type="real" size="1">
 7.309165792514261E+001
    </BULK_MODULUS_KBAR>
    <DERIVATIVE_BULK_MODULUS type="real" size="1">
 3.799008111060536E+000
    </DERIVATIVE_BULK_MODULUS>
    <SECOND_DERIVATIVE_BULK_MODULUS type="real" size="1">
 0.000000000000000E+000
    </SECOND_DERIVATIVE_BULK_MODULUS>
    <MINIMUM_ENERGY_RY type="real" size="1">
-9.510565923128210E+001
    </MINIMUM_ENERGY_RY>
    <CELL_FACTOR type="real" size="1">
 2.500000000000000E-001
    </CELL_FACTOR>
    <CELL_PARAMETER_AU_A type="real" size="2" columns="2">
 1.005197701334935E+001  5.319277136735056E+000
    </CELL_PARAMETER_AU_A>
  </EQUATIONS_PARAMETERS>
  <FIT_CHECK>
    <NUMBER_OF_DATA type="integer" size="1">
        16
    </NUMBER_OF_DATA>
    <VOL_ENE_EFIT_DELTA_P_GIBBS type="real" size="96" columns="6">
 1.481820736055420E+002 -9.508032155715027E+001 -9.508032482777273E+001  3.270622457307581E-006  1.086418252751773E+002 -9.497088431818544E+001 
 1.618036562500000E+002 -9.508884934164440E+001 -9.508884374135141E+001 -5.600292993790390E-006  7.711921287844768E+001 -9.500402444766573E+001 
 1.744744861711648E+002 -9.509452338296552E+001 -9.509452061337088E+001 -2.769594644291828E-006  5.574555527436618E+001 -9.502840616369178E+001 
 1.828581752500000E+002 -9.509737172139893E+001 -9.509737164134599E+001 -8.005294205304381E-008  4.465277753400641E+001 -9.504186631763027E+001 
 1.915152187500000E+002 -9.509970866260844E+001 -9.509971135881777E+001  2.696209335795174E-006  3.516019974262102E+001 -9.505393380198298E+001 
 2.004522399750655E+002 -9.510159076561089E+001 -9.510159314534268E+001  2.379731782298222E-006  2.704441748688662E+001 -9.506473877503699E+001 
 2.076460000000000E+002 -9.510277419811186E+001 -9.510277747045706E+001  3.272345196592141E-006  2.152870748847521E+001 -9.507238537139904E+001 
 2.143437500000000E+002 -9.510365380226258E+001 -9.510365399573030E+001  1.934677129611373E-007  1.707508359258829E+001 -9.507877404899227E+001 
 2.211840000000000E+002 -9.510434966205779E+001 -9.510435360001277E+001  3.937954986099612E-006  1.310643420702429E+001 -9.508464310905737E+001 
 2.281682499999999E+002 -9.510488783718333E+001 -9.510489007763762E+001  2.240454293200855E-006  9.573588802894449E+000 -9.509003866005648E+001 
 2.412875230954168E+002 -9.510549012712139E+001 -9.510548989025391E+001 -2.368674785202529E-007  4.108794779683548E+000 -9.509875071954690E+001 
 2.477457206488650E+002 -9.510562386506528E+001 -9.510562045495853E+001 -3.410106756973619E-006  1.884905498248277E+000 -9.510244941756493E+001 
 2.515030020000000E+002 -9.510565988678810E+001 -9.510565343441533E+001 -6.452372772969284E-006  7.114621201249738E-001 -9.510444351213521E+001 
 2.715934879999999E+002 -9.510538862365959E+001 -9.510538485804867E+001 -3.765610927075613E-006 -4.327983190067709E+000 -9.511337918563204E+001 
 2.812160000000001E+002 -9.510504265088284E+001 -9.510504049866043E+001 -2.152222407403315E-006 -6.146294636315721E+000 -9.511679232463794E+001 
 2.894062500000000E+002 -9.510465443971719E+001 -9.510466091605251E+001  6.476335315142023E-006 -7.455535059965619E+000 -9.511932204211769E+001
    </VOL_ENE_EFIT_DELTA_P_GIBBS>
  </FIT_CHECK>
</Root>

