<?xml version="1.0"?>
<?iotk version="1.2.0"?>
<?iotk file_version="1.0"?>
<?iotk binary="F"?>
<?iotk qe_syntax="F"?>
<Root>
  <EQUATIONS_OF_STATE>
    <EQUATION_TYPE type="character" size="1" len="15">
Birch 1st order
    </EQUATION_TYPE>
    <CHI_SQUARE type="real" size="1">
 2.203776701426940E-011
    </CHI_SQUARE>
  </EQUATIONS_OF_STATE>
  <EQUATIONS_PARAMETERS>
    <EQUILIBRIUM_VOLUME_AU_A type="real" size="2" columns="2">
 2.522900213108958E+002  3.738552352503164E+001
    </EQUILIBRIUM_VOLUME_AU_A>
    <BULK_MODULUS_KBAR type="real" size="1">
 7.548194818108614E+001
    </BULK_MODULUS_KBAR>
    <DERIVATIVE_BULK_MODULUS type="real" size="1">
 3.759335774657750E+000
    </DERIVATIVE_BULK_MODULUS>
    <SECOND_DERIVATIVE_BULK_MODULUS type="real" size="1">
 0.000000000000000E+000
    </SECOND_DERIVATIVE_BULK_MODULUS>
    <MINIMUM_ENERGY_RY type="real" size="1">
-9.510532344946412E+001
    </MINIMUM_ENERGY_RY>
    <CELL_FACTOR type="real" size="1">
 5.000000000000000E-001
    </CELL_FACTOR>
    <CELL_PARAMETER_AU_A type="real" size="2" columns="2">
 7.961166185532328E+000  4.212867699181094E+000
    </CELL_PARAMETER_AU_A>
  </EQUATIONS_PARAMETERS>
  <FIT_CHECK>
    <NUMBER_OF_DATA type="integer" size="1">
        16
    </NUMBER_OF_DATA>
    <VOL_ENE_EFIT_DELTA_P_GIBBS type="real" size="96" columns="6">
 1.494566723736112E+002 -9.508118415414118E+001 -9.508118902706489E+001  4.872923710763644E-006  1.046519361690032E+002 -9.497485925428222E+001 
 1.628303360000000E+002 -9.508927954444458E+001 -9.508927073333285E+001 -8.811111726458876E-006  7.475469903245339E+001 -9.500653369426125E+001 
 1.767341968128358E+002 -9.509521641968954E+001 -9.509521500008292E+001 -1.419606618924263E-006  5.222404086489365E+001 -9.503247368132372E+001 
 1.866240000000000E+002 -9.509830160806044E+001 -9.509829968268333E+001 -1.925377105749249E-006  3.998451255618502E+001 -9.504757548093266E+001 
 2.010081871451615E+002 -9.510149940317862E+001 -9.510150383881937E+001  4.435640747146863E-006  2.624754788785344E+001 -9.506563406834603E+001 
 2.034345105000000E+002 -9.510191860063878E+001 -9.510192066194561E+001  2.061306830114518E-006  2.431156968109876E+001 -9.506829764648084E+001 
 2.067468125000000E+002 -9.510243768462732E+001 -9.510243970486611E+001  2.020238795807927E-006  2.181978361303867E+001 -9.507177136427870E+001 
 2.109375000000000E+002 -9.510301701715466E+001 -9.510301910675064E+001  2.089595980692138E-006  1.889890807468903E+001 -9.507591741511446E+001 
 2.186227395000000E+002 -9.510387353044287E+001 -9.510387902198907E+001  5.491546204439146E-006  1.414264365815009E+001 -9.508285519411891E+001 
 2.264924160000000E+002 -9.510451994083193E+001 -9.510452108152320E+001  1.140691267664806E-006  9.968665848823321E+000 -9.508917154082312E+001 
 2.309449585000000E+002 -9.510478645975184E+001 -9.510479069738572E+001  4.237633888237724E-006  7.876912744397803E+000 -9.509242024093632E+001 
 2.354554760000000E+002 -9.510500612170429E+001 -9.510500200303012E+001 -4.118674169717451E-006  5.934246774187864E+000 -9.509550780155317E+001 
 2.435633953414749E+002 -9.510524782620476E+001 -9.510524156705212E+001 -6.259152641518995E-006  2.838779537014924E+000 -9.510054762887113E+001 
 2.569612005000000E+002 -9.510530780669389E+001 -9.510530189747303E+001 -5.909220860189635E-006 -1.337825081562672E+000 -9.510764470219561E+001 
 2.757253772625645E+002 -9.510484353007145E+001 -9.510483864126236E+001 -4.888809087333357E-006 -5.672540651799124E+000 -9.511547581882380E+001 
 2.963520000000000E+002 -9.510379007881717E+001 -9.510379706119174E+001  6.982374571862238E-006 -8.971835252733829E+000 -9.512186438182842E+001
    </VOL_ENE_EFIT_DELTA_P_GIBBS>
  </FIT_CHECK>
</Root>

