<?xml version="1.0"?>
<?iotk version="1.2.0"?>
<?iotk file_version="1.0"?>
<?iotk binary="F"?>
<?iotk qe_syntax="F"?>
<Root>
  <EQUATIONS_OF_STATE>
    <EQUATION_TYPE type="character" size="1" len="15">
Birch 1st order
    </EQUATION_TYPE>
    <CHI_SQUARE type="real" size="1">
 3.636618136680878E-011
    </CHI_SQUARE>
  </EQUATIONS_OF_STATE>
  <EQUATIONS_PARAMETERS>
    <EQUILIBRIUM_VOLUME_AU_A type="real" size="2" columns="2">
 2.560438764028045E+002  3.794178745144025E+001
    </EQUILIBRIUM_VOLUME_AU_A>
    <BULK_MODULUS_KBAR type="real" size="1">
 7.131942516018348E+001
    </BULK_MODULUS_KBAR>
    <DERIVATIVE_BULK_MODULUS type="real" size="1">
 3.791498854381847E+000
    </DERIVATIVE_BULK_MODULUS>
    <SECOND_DERIVATIVE_BULK_MODULUS type="real" size="1">
 0.000000000000000E+000
    </SECOND_DERIVATIVE_BULK_MODULUS>
    <MINIMUM_ENERGY_RY type="real" size="1">
-9.510690852691296E+001
    </MINIMUM_ENERGY_RY>
    <CELL_FACTOR type="real" size="1">
 5.000000000000000E-001
    </CELL_FACTOR>
    <CELL_PARAMETER_AU_A type="real" size="2" columns="2">
 8.000457019753666E+000  4.233659513157515E+000
    </CELL_PARAMETER_AU_A>
  </EQUATIONS_PARAMETERS>
  <FIT_CHECK>
    <NUMBER_OF_DATA type="integer" size="1">
        18
    </NUMBER_OF_DATA>
    <VOL_ENE_EFIT_DELTA_P_GIBBS type="real" size="108" columns="6">
 1.494566723736112E+002 -9.508204658052075E+001 -9.508204840592009E+001  1.825399337462841E-006  1.056415622409711E+002 -9.497471623444787E+001 
 1.628303360000000E+002 -9.509022069599129E+001 -9.509021805967515E+001 -2.636316139614792E-006  7.571116273305324E+001 -9.500641613775215E+001 
 1.767341968128358E+002 -9.509624285542961E+001 -9.509625310654303E+001  1.025111342300988E-005  5.319311276915060E+001 -9.503233585968464E+001 
 1.827629375000000E+002 -9.509828369458097E+001 -9.509827048175120E+001 -1.321282977073679E-005  4.543031476838783E+001 -9.504184118936581E+001 
 1.866240000000000E+002 -9.509941047987486E+001 -9.509940357739737E+001 -6.902477494463710E-006  4.097326330039414E+001 -9.504742997967256E+001 
 1.937102445000000E+002 -9.510120130732932E+001 -9.510119770279832E+001 -3.604531002565636E-006  3.369998997596515E+001 -9.505682463148059E+001 
 2.010081871451615E+002 -9.510270220853822E+001 -9.510270594975458E+001  3.741216360708677E-006  2.726748864754970E+001 -9.506544320001801E+001 
 2.034345105000000E+002 -9.510313660452788E+001 -9.510313963695141E+001  3.032423535387352E-006  2.533650223034931E+001 -9.506809825072419E+001 
 2.067468125000000E+002 -9.510367808961612E+001 -9.510368183238310E+001  3.742766978120926E-006  2.285128703222423E+001 -9.507156205671056E+001 
 2.109375000000000E+002 -9.510428524584496E+001 -9.510429073257069E+001  5.486725726200348E-006  1.993826211916085E+001 -9.507569528886613E+001 
 2.186227395000000E+002 -9.510519857077250E+001 -9.510520529222238E+001  6.721449878455132E-006  1.519486932074616E+001 -9.508261645094386E+001 
 2.264924160000000E+002 -9.510590065583870E+001 -9.510590394608239E+001  3.290243697051665E-006  1.103185131912252E+001 -9.508891530700150E+001 
 2.309449585000000E+002 -9.510620328973512E+001 -9.510620582240796E+001  2.532672837673999E-006  8.945274484382077E+000 -9.509215981544153E+001 
 2.354554760000000E+002 -9.510645145873509E+001 -9.510644995682770E+001 -1.501907391343593E-006  7.007101371553375E+000 -9.509523593388569E+001 
 2.435633953414749E+002 -9.510675560086980E+001 -9.510674883516489E+001 -6.765704910094428E-006  3.917859783638778E+000 -9.510026875894761E+001 
 2.569612005000000E+002 -9.510691633570487E+001 -9.510690773477577E+001 -8.600929092494880E-006 -2.533348346761738E-001 -9.510735885770849E+001 
 2.757253772625645E+002 -9.510658647418494E+001 -9.510658282998671E+001 -3.644198230290385E-006 -4.589336649417501E+000 -9.511518846673705E+001 
 2.963520000000000E+002 -9.510568622683009E+001 -9.510569247171216E+001  6.244882072792279E-006 -7.899490055427996E+000 -9.512160022579174E+001
    </VOL_ENE_EFIT_DELTA_P_GIBBS>
  </FIT_CHECK>
</Root>

