<?xml version="1.0"?>
<?iotk version="1.2.0"?>
<?iotk file_version="1.0"?>
<?iotk binary="F"?>
<?iotk qe_syntax="F"?>
<Root>
  <EQUATIONS_OF_STATE>
    <EQUATION_TYPE type="character" size="1" len="15">
Birch 1st order
    </EQUATION_TYPE>
    <CHI_SQUARE type="real" size="1">
 5.620055784433054E-010
    </CHI_SQUARE>
  </EQUATIONS_OF_STATE>
  <EQUATIONS_PARAMETERS>
    <EQUILIBRIUM_VOLUME_AU_A type="real" size="2" columns="2">
 2.528919897058177E+002  3.747472603677881E+001
    </EQUILIBRIUM_VOLUME_AU_A>
    <BULK_MODULUS_KBAR type="real" size="1">
 7.672797871222976E+001
    </BULK_MODULUS_KBAR>
    <DERIVATIVE_BULK_MODULUS type="real" size="1">
 3.677624552361614E+000
    </DERIVATIVE_BULK_MODULUS>
    <SECOND_DERIVATIVE_BULK_MODULUS type="real" size="1">
 0.000000000000000E+000
    </SECOND_DERIVATIVE_BULK_MODULUS>
    <MINIMUM_ENERGY_RY type="real" size="1">
-9.510578776784125E+001
    </MINIMUM_ENERGY_RY>
    <CELL_FACTOR type="real" size="1">
 5.000000000000000E-001
    </CELL_FACTOR>
    <CELL_PARAMETER_AU_A type="real" size="2" columns="2">
 7.967492983411139E+000  4.216215696421918E+000
    </CELL_PARAMETER_AU_A>
  </EQUATIONS_PARAMETERS>
  <FIT_CHECK>
    <NUMBER_OF_DATA type="integer" size="1">
         5
    </NUMBER_OF_DATA>
    <VOL_ENE_EFIT_DELTA_P_GIBBS type="real" size="30" columns="6">
 1.494566723736112E+002 -9.508138420121170E+001 -9.508138645658143E+001  2.255369722092837E-006  1.043429646836382E+002 -9.497537321204989E+001 
 1.767341968128358E+002 -9.509546679140091E+001 -9.509545400751510E+001 -1.278388580772116E-005  5.274502685148739E+001 -9.503209813273273E+001 
 2.010081871451615E+002 -9.510180979269124E+001 -9.510183564228838E+001  2.584959713658463E-005  2.679771871648073E+001 -9.506519269007188E+001 
 2.435633953414749E+002 -9.510566981978991E+001 -9.510569262188247E+001  2.280209255900445E-005  3.089980964897329E+000 -9.510055370559266E+001 
 2.757253772625645E+002 -9.510535633796835E+001 -9.510531821479474E+001 -3.812317360996076E-005 -5.655884022647819E+000 -9.511595740647888E+001
    </VOL_ENE_EFIT_DELTA_P_GIBBS>
  </FIT_CHECK>
</Root>

