<?xml version="1.0"?>
<?iotk version="1.2.0"?>
<?iotk file_version="1.0"?>
<?iotk binary="F"?>
<?iotk qe_syntax="F"?>
<Root>
  <EQUATIONS_OF_STATE>
    <EQUATION_TYPE type="character" size="1" len="15">
Birch 1st order
    </EQUATION_TYPE>
    <CHI_SQUARE type="real" size="1">
 2.953364248825008E-011
    </CHI_SQUARE>
  </EQUATIONS_OF_STATE>
  <EQUATIONS_PARAMETERS>
    <EQUILIBRIUM_VOLUME_AU_A type="real" size="2" columns="2">
 2.770739363541214E+002  4.105812077670455E+001
    </EQUILIBRIUM_VOLUME_AU_A>
    <BULK_MODULUS_KBAR type="real" size="1">
 9.836507177619831E+002
    </BULK_MODULUS_KBAR>
    <DERIVATIVE_BULK_MODULUS type="real" size="1">
 1.000000139350860E+000
    </DERIVATIVE_BULK_MODULUS>
    <SECOND_DERIVATIVE_BULK_MODULUS type="real" size="1">
 0.000000000000000E+000
    </SECOND_DERIVATIVE_BULK_MODULUS>
    <MINIMUM_ENERGY_RY type="real" size="1">
-1.918784207152358E+001
    </MINIMUM_ENERGY_RY>
    <CELL_FACTOR type="real" size="1">
 2.500000000000000E-001
    </CELL_FACTOR>
    <CELL_PARAMETER_AU_A type="real" size="2" columns="2">
 1.034868629164972E+001  5.476288924388798E+000
    </CELL_PARAMETER_AU_A>
  </EQUATIONS_PARAMETERS>
  <FIT_CHECK>
    <NUMBER_OF_DATA type="integer" size="1">
         4
    </NUMBER_OF_DATA>
    <VOL_ENE_EFIT_DELTA_P_GIBBS type="real" size="24" columns="6">
 2.715934879999999E+002 -1.918747734699816E+001 -1.918747491693872E+001 -2.430059435454268E-006  1.983557974206564E+001 -1.915085580245239E+001 
 2.725457042720000E+002 -1.918758468171505E+001 -1.918759197324541E+001  7.291530362607546E-006  1.633548179769189E+001 -1.915731947144830E+001 
 2.735001436160001E+002 -1.918769393075846E+001 -1.918768663967238E+001 -7.291086081551157E-006  1.284961628055242E+001 -1.916380371215525E+001 
 2.744568086240000E+002 -1.918775647499596E+001 -1.918775890461112E+001  2.429615157950593E-006  9.378353671206819E+000 -1.917025909507303E+001
    </VOL_ENE_EFIT_DELTA_P_GIBBS>
  </FIT_CHECK>
</Root>

